flask_prom_metrics/__init__.py
flask_prom_metrics/flask_prom_metrics.py
flask_prom_metrics-0.1.9.dist-info/LICENSE
flask_prom_metrics-0.1.9.dist-info/METADATA
flask_prom_metrics-0.1.9.dist-info/WHEEL
flask_prom_metrics-0.1.9.dist-info/top_level.txt
flask_prom_metrics-0.1.9.dist-info/RECORD
