Metadata-Version: 2.1
Name: flask-prom-metrics
Version: 0.1.9
Summary: Export prometheus metrics for Flask applications
Home-page: https://github.com/7onn/flask-prom-metrics
Author: Tom M G
Author-email: devbytom@gmail.com
License: UNKNOWN
Project-URL: Bug Tracker, https://github.com/7onn/flask-prom-metrics/issues
Platform: UNKNOWN
Classifier: Programming Language :: Python :: 3
Classifier: License :: OSI Approved :: GNU General Public License v3 (GPLv3)
Classifier: Operating System :: OS Independent
Requires-Python: >=3.6
License-File: LICENSE
